galpak/__init__.py
galpak/__version__.py
galpak/ansi_colors.py
galpak/api.py
galpak/convolution.py
galpak/fits_sanitizer.py
galpak/galaxy_parameter.py
galpak/galaxy_parameters.py
galpak/galpak3d.py
galpak/galpak3d_utils.py
galpak/hyperspectral_cube.py
galpak/instruments.py
galpak/math_utils.py
galpak/mcmc.py
galpak/model_class.py
galpak/model_sersic3d.py
galpak/model_utilities.py
galpak/plot_utilities.py
galpak/spread_functions.py
galpak/string_stdout.py
galpak-1.35.2.dist-info/LICENCE
galpak-1.35.2.dist-info/METADATA
galpak-1.35.2.dist-info/WHEEL
galpak-1.35.2.dist-info/top_level.txt
galpak-1.35.2.dist-info/RECORD
